modelchimp
