Metadata-Version: 1.0
Name: modelchimp
Version: 0.5.6
Summary: Python client to upload the machine learning models data to the model chimp cloud
Home-page: https://www.modelchimp.com
Author: Samir Madhavan
Author-email: samir.madhavan@gmail.com
License: UNKNOWN
Keywords: modelchimp,ai,datascience
Platform: UNKNOWN
